gurmukhiutils/__init__.py
gurmukhiutils/ascii.py
gurmukhiutils/constants.py
gurmukhiutils/convert.py
gurmukhiutils/converters/__init__.py
gurmukhiutils/converters/guru_latn.py
gurmukhiutils/converters/guru_latn_pa.py
gurmukhiutils/remove.py
gurmukhiutils/unicode.py
gurmukhiutils-0.3.1.dist-info/METADATA
gurmukhiutils-0.3.1.dist-info/WHEEL
gurmukhiutils-0.3.1.dist-info/LICENSE
gurmukhiutils-0.3.1.dist-info/RECORD
