Metadata-Version: 2.1
Name: gurmukhiutils
Version: 0.3.1
Summary: Python utilities library for converting, analyzing, and testing Gurmukhi strings
Home-page: https://github.com/shabados/gurmukhiutils
License: MIT
Keywords: gurbani,gurmukhi,sikh,transliterate,unicode
Author: Bhajneet S.K.
Author-email: bhajneet@gmail.com
Maintainer: Bhajneet S.K.
Maintainer-email: bhajneet@gmail.com
Requires-Python: >=3.10,<4.0
Classifier: Development Status :: 1 - Planning
Classifier: Intended Audience :: Developers
Classifier: License :: OSI Approved :: MIT License
Classifier: Natural Language :: Panjabi
Classifier: Operating System :: MacOS
Classifier: Operating System :: Microsoft :: Windows
Classifier: Operating System :: POSIX :: Linux
Classifier: Programming Language :: Python :: 3
Classifier: Programming Language :: Python :: 3.10
Classifier: Programming Language :: Python :: 3.11
Classifier: Topic :: Software Development :: Internationalization
Classifier: Topic :: Software Development :: Libraries
Classifier: Topic :: Text Processing
Classifier: Topic :: Utilities
Project-URL: Bug Tracker, https://github.com/shabados/gurmukhiutils/issues
Project-URL: Documentation, https://github.com/shabados/gurmukhiutils
Project-URL: Repository, https://github.com/shabados/gurmukhiutils
